python_workflow_plugin_framework/__init__.py
python_workflow_plugin_framework/base_plugin.py
python_workflow_plugin_framework/node_plugin_pb2.py
python_workflow_plugin_framework/node_plugin_pb2_grpc.py
python_workflow_plugin_framework-1.2.0.dist-info/licenses/LICENSE
python_workflow_plugin_framework-1.2.0.dist-info/METADATA
python_workflow_plugin_framework-1.2.0.dist-info/WHEEL
python_workflow_plugin_framework-1.2.0.dist-info/top_level.txt
python_workflow_plugin_framework-1.2.0.dist-info/RECORD
