Metadata-Version: 2.4
Name: python-workflow-plugin-framework
Version: 1.2.0
Summary: 一个简化 Python 插件开发的通用框架
Home-page: https://github.com/yourusername/python-plugin-framework
Author: gw123
Author-email: 963383840@qq.com
Classifier: Programming Language :: Python :: 3
Classifier: License :: OSI Approved :: MIT License
Classifier: Operating System :: OS Independent
Classifier: Development Status :: 4 - Beta
Classifier: Intended Audience :: Developers
Classifier: Topic :: Software Development :: Libraries :: Application Frameworks
Requires-Python: >=3.8
License-File: LICENSE
Requires-Dist: grpcio>=1.60.0
Requires-Dist: glog-python==1.0.1
Requires-Dist: requests>=2.31.0
Requires-Dist: langchain>=0.1.0
Requires-Dist: ollama>=0.1.0
Dynamic: author
Dynamic: author-email
Dynamic: classifier
Dynamic: description
Dynamic: description-content-type
Dynamic: home-page
Dynamic: license-file
Dynamic: requires-dist
Dynamic: requires-python
Dynamic: summary
